pynetmanager/CliManager.py
pynetmanager/NetCallback.py
pynetmanager/RawSockManager.py
pynetmanager/SvrManager.py
pynetmanager/__init__.py
pynetmanager-1.0.0.dist-info/LICENSE
pynetmanager-1.0.0.dist-info/METADATA
pynetmanager-1.0.0.dist-info/WHEEL
pynetmanager-1.0.0.dist-info/top_level.txt
pynetmanager-1.0.0.dist-info/RECORD
