Metadata-Version: 2.1
Name: pynetmanager
Version: 1.0.0
Summary: A FOSS library to simplify writing and handling sockets in Python. Includes INET and INET6 support, `bind`, `listen`, `accept`, `connect` API.
Home-page: https://github.com/AdityaIyer2k7/pynetmanager
Author: AdityaIyer2k7
Author-email: adityaiyer2007@gmail.com
Keywords: python,python 3,socket,sockets,network,networks,networking
Classifier: Programming Language :: Python :: 3
Classifier: License :: OSI Approved :: GNU General Public License v3 (GPLv3)
Classifier: Operating System :: OS Independent
Classifier: Topic :: Utilities
Requires-Python: >=3.6
License-File: LICENSE
